cloaca_sqlite-0.2.0.dist-info/METADATA
cloaca_sqlite-0.2.0.dist-info/WHEEL
cloaca_sqlite.libs/libcom_err-022943b3.so.2
cloaca_sqlite.libs/libcrypto-fca80f7e.so.3
cloaca_sqlite.libs/libffi-00f593fe.so.8
cloaca_sqlite.libs/libgmp-0ccdfb6d.so.10
cloaca_sqlite.libs/libgnutls-a64da3b2.so.30
cloaca_sqlite.libs/libgssapi_krb5-b9a20df7.so.2
cloaca_sqlite.libs/libhogweed-c3c60613.so.6
cloaca_sqlite.libs/libidn2-6e632fd9.so.0
cloaca_sqlite.libs/libk5crypto-8394027f.so.3
cloaca_sqlite.libs/libkeyutils-f4821441.so.1
cloaca_sqlite.libs/libkrb5-52c143c9.so.3
cloaca_sqlite.libs/libkrb5support-8e1ef5a4.so.0
cloaca_sqlite.libs/liblber-6f6935b2.so.2
cloaca_sqlite.libs/libldap-4a0664ab.so.2
cloaca_sqlite.libs/libnettle-a245ed91.so.8
cloaca_sqlite.libs/libp11-kit-c6b469a0.so.0
cloaca_sqlite.libs/libpq-09ee2eac.so.5
cloaca_sqlite.libs/libsasl2-a0f410ad.so.2
cloaca_sqlite.libs/libsqlite3-cb9a664c.so.0
cloaca_sqlite.libs/libssl-e50e007b.so.3
cloaca_sqlite.libs/libtasn1-7c9c7830.so.6
cloaca_sqlite.libs/libunistring-7bcf825c.so.5
cloaca_sqlite/__init__.py
cloaca_sqlite/cloaca_sqlite.abi3.so
cloaca_sqlite-0.2.0.dist-info/RECORD
