Metadata-Version: 2.4
Name: cloaca-sqlite
Version: 0.2.0
Classifier: Development Status :: 3 - Alpha
Classifier: Intended Audience :: Developers
Classifier: License :: OSI Approved :: MIT License
Classifier: License :: OSI Approved :: Apache Software License
Classifier: Programming Language :: Python :: 3
Classifier: Programming Language :: Python :: 3.9
Classifier: Programming Language :: Python :: 3.10
Classifier: Programming Language :: Python :: 3.11
Classifier: Programming Language :: Python :: 3.12
Classifier: Programming Language :: Rust
Classifier: Topic :: Software Development :: Libraries :: Python Modules
Classifier: Topic :: System :: Distributed Computing
Classifier: Topic :: Database :: Database Engines/Servers
Summary: Sqlite backend for Cloaca - Python bindings for Cloacina workflow orchestration
Author-email: Cloacina Team <team@cloacina.dev>
License: MIT OR Apache-2.0
Requires-Python: >=3.9
Project-URL: Homepage, https://github.com/dstorey/cloacina
Project-URL: Repository, https://github.com/dstorey/cloacina
Project-URL: Documentation, https://cloacina.dev
Project-URL: Issues, https://github.com/dstorey/cloacina/issues
